SortingAlgorithms/Algorithms.py
SortingAlgorithms/__init__.py
SortingAlgorithms-1.0.dist-info/LICENSE
SortingAlgorithms-1.0.dist-info/METADATA
SortingAlgorithms-1.0.dist-info/WHEEL
SortingAlgorithms-1.0.dist-info/top_level.txt
SortingAlgorithms-1.0.dist-info/RECORD
