Metadata-Version: 2.1
Name: SortingAlgorithms
Version: 1.0
Summary: This package will help user to get the results of few sorting algorithms.
Home-page: https://github.com/abhi7585/SortingAlgorithms
Author: Abhishek Tripathi
Author-email: abhi.workonly@gmail.com
License: MIT
Platform: UNKNOWN
Classifier: License :: OSI Approved :: MIT License
Classifier: Programming Language :: Python
